smart_word_cloud/__init__.py
smart_word_cloud/smart_word_cloud.py
smart_word_cloud-0.1.dist-info/LICENSE
smart_word_cloud-0.1.dist-info/METADATA
smart_word_cloud-0.1.dist-info/WHEEL
smart_word_cloud-0.1.dist-info/top_level.txt
smart_word_cloud-0.1.dist-info/RECORD
