Metadata-Version: 2.1
Name: smart_word_cloud
Version: 0.1
Summary: Generate smart word cloud.
Home-page: https://github.com/Yewei-Liu/smart_word_cloud.git
Author: 刘晔玮  Yewei Liu (Lewis)
Author-email: liuyeweilewis@gmail.com
License: MIT
License-File: LICENSE
